mcp_time_server/__init__.py
mcp_time_server/cli.py
mcp_cuc_king-0.1.0.dist-info/METADATA
mcp_cuc_king-0.1.0.dist-info/WHEEL
mcp_cuc_king-0.1.0.dist-info/entry_points.txt
mcp_cuc_king-0.1.0.dist-info/licenses/LICENSE
mcp_cuc_king-0.1.0.dist-info/RECORD
