Metadata-Version: 2.4
Name: mcp-cuc-king
Version: 0.1.0
Summary: MCP Server for getting current time with timezone support
Project-URL: Homepage, https://github.com/yourusername/mcp-time-server
Project-URL: Repository, https://github.com/yourusername/mcp-time-server
Project-URL: Issues, https://github.com/yourusername/mcp-time-server/issues
Author-email: Your Name <your.email@example.com>
License: MIT
License-File: LICENSE
Requires-Python: >=3.10
Requires-Dist: mcp>=1.0.0
Requires-Dist: pytz>=2024.1
